Events/IGroupEvents.py
Events/IGroupsEvents.py
Events/IServerEvents.py
Events/__init__.py
Interfaces/IOPCBase.py
Interfaces/IOPCBrowser.py
Interfaces/IOPCGroup.py
Interfaces/IOPCGroups.py
Interfaces/IOPCItem.py
Interfaces/IOPCItems.py
Interfaces/IOPCServer.py
Interfaces/__init__.py
Structs/OPCBase.py
Structs/OPCBrowser.py
Structs/OPCGroup.py
Structs/OPCGroups.py
Structs/OPCItem.py
Structs/OPCItems.py
Structs/OPCServer.py
Structs/__init__.py
OpcDa-0.1.dist-info/METADATA
OpcDa-0.1.dist-info/WHEEL
OpcDa-0.1.dist-info/top_level.txt
OpcDa-0.1.dist-info/RECORD
