Metadata-Version: 2.1
Name: OpcDa
Version: 0.1
Summary: Package to OPC
Home-page: http://github.com/storborg/funniest
Author: Pockusaev Andrey
Author-email: pockusaevandrey@yandex.ru
License: MIT
Keywords: opc da
Platform: UNKNOWN
Classifier: Development Status :: 3 - Alpha
Classifier: License :: OSI Approved :: MIT License
Classifier: Programming Language :: Python :: 3.7
Classifier: Topic :: Text Processing :: Linguistic
Requires-Dist: pypiwin32
